AIDSTK/__init__.py
AIDSTK/functions.py
AIDSTK/models.py
AIDSTK/configs/config1.json
AIDSTK/configs/config2.json
AIDSTK/configs/gemma2_T1_00.json
AIDSTK/configs/llama3_1_T0_00.json
AIDSTK/configs/llama3_2_T0_80.json
AIDSTK/prompts/IT_Categorizer.txt
AIDSTK/prompts/Sentiment_Analyzer.txt
AIDSTK/prompts/prompt1.txt
AIDSTK/prompts/prompt2.txt
AIDSTK-0.2.0.dist-info/LICENSE
AIDSTK-0.2.0.dist-info/METADATA
AIDSTK-0.2.0.dist-info/WHEEL
AIDSTK-0.2.0.dist-info/top_level.txt
AIDSTK-0.2.0.dist-info/RECORD
