Metadata-Version: 2.1
Name: AIDSTK
Version: 0.2.0
Summary: A modular and flexible AI library for processing text data
Home-page: https://github.com/amendoxa/AIDSTK
Author: Alex Mendoza
Author-email: alexander.mendoza.am@gmail.com
Classifier: Programming Language :: Python :: 3
Classifier: License :: OSI Approved :: MIT License
Classifier: Operating System :: OS Independent
Requires-Python: >=3.6
License-File: LICENSE
Requires-Dist: langchain-community
Requires-Dist: pandas
Requires-Dist: tqdm
